{"quest":{"name":"The Hour of Reckoning","location":"The Azim Steppe","id":68054,"patch":4.0,"sort":760,"eventIcon":71201,"issuer":1021647,"target":1020519,"involved":[1019285,1019288,1020520,1020521,1020522,1020523,1020524,1021648,1021649,1021651,1021652,1021653,1021692,1021693],"genre":6,"journal":["The time has come for Lord Hien to return to Doma."],"objectives":["Speak with Gosetsu.","Speak with Hien.","Speak with Alphinaud."],"dialogue":[{"name":"LYSE","text":"Let's go. Everyone is waiting for us back at the House of the Fierce!"},{"name":"GOSETSU","text":"Heh heh...I wonder what Yugiri will have to say when we tell her of our adventures?"},{"name":"HIEN","text":"Right, then. To the House of the Fierce. With me, my friends!"},{"name":"LYSE","text":"Err, remind me─what part of Yanxia is this again?"},{"name":"HIEN","text":"Ahh...this air that fills my breast, these sounds which resound in my ears. I am home."},{"name":"GOSETSU","text":"I have not used this road before, but... Ah. I recognize this place."},{"name":"GOSETSU","text":"The House of the Fierce should lie somewhere to the south. I will go on ahead and inform the sentries of our master's return."},{"name":"LYSE","text":"Huh, I didn't realize there was another entrance."},{"name":"HIEN","text":"Here we are! I wonder if they all are gathered inside, waiting...perhaps expecting a speech or some such..."},{"name":"HIEN","text":"Well! No matter! I shall have to do what I shall have to do!"},{"name":"LYSE","text":"So...have we got a plan? Tell me someone's got a plan."},{"name":"ALISAIE","text":"Alphinaud has been hard at work devising our strategy to seize Doma Castle. I'm sure he will be happy to share the details with you all shortly."},{"name":"HIEN","text":"No time to soak it in. We have work to do."},{"name":"YUGIRI","text":"Not that I doubted you for a moment, but I am relieved to see him returned."},{"name":"GOSETSU","text":"All is in place. We need but commit to action and see it through to the end."},{"name":"YAGORO","text":"Lord Hien has returned! Lord Hien has returned! And together we will drive the imperials out of Doma once and for all!"},{"name":"HANAME","text":"I knew Lord Hien only by name and reputation until today. There is no denying that he has a presence..."},{"name":"ALPHINAUD","text":"Once more, welcome back. It is good to see you again, <span class=\"highlight\">Forename</span>."},{"name":"ALPHINAUD","text":"Ah, yes. There is another recent development we neglected to share with you."},{"name":"ALPHINAUD","text":"Alisaie and I have been hard at work attempting to restore the aetheryte here to its former glory...and I am pleased to inform you that we succeeded!"},{"name":"ALPHINAUD","text":"Suffice it to say, it should prove a boon for travel─well, for those replete with anima like you, at least..."}],"reward":{"gil":760,"xp":216000},"reqs":{"jobs":[{"lvl":66,"id":142}],"quests":[68053]},"next":[68055]},"partials":[{"type":"npc","id":"1021647","obj":{"i":1021647,"n":"Hien","l":2411,"q":2}},{"type":"npc","id":"1020519","obj":{"i":1020519,"n":"Alphinaud","l":2410,"q":8}},{"type":"npc","id":"1019285","obj":{"i":1019285,"n":"Haname","l":2410,"q":5}},{"type":"npc","id":"1019288","obj":{"i":1019288,"n":"Yagoro","l":2410,"q":3}},{"type":"npc","id":"1020520","obj":{"i":1020520,"n":"Alisaie","l":2410,"q":6}},{"type":"npc","id":"1020521","obj":{"i":1020521,"n":"Lyse","l":2410,"q":5}},{"type":"npc","id":"1020522","obj":{"i":1020522,"n":"Gosetsu","l":2410,"q":2}},{"type":"npc","id":"1020523","obj":{"i":1020523,"n":"Yugiri","l":2410,"q":8}},{"type":"npc","id":"1020524","obj":{"i":1020524,"n":"Hien","l":2410,"q":6}},{"type":"npc","id":"1021648","obj":{"i":1021648,"n":"Gosetsu","l":2411,"q":2}},{"type":"npc","id":"1021649","obj":{"i":1021649,"n":"Lyse","l":2411,"q":2}},{"type":"npc","id":"1021651","obj":{"i":1021651,"n":"Hien","l":2410,"q":1}},{"type":"npc","id":"1021652","obj":{"i":1021652,"n":"Gosetsu","l":2410,"q":1}},{"type":"npc","id":"1021653","obj":{"i":1021653,"n":"Lyse","l":2410,"q":1}},{"type":"npc","id":"1021692","obj":{"i":1021692,"n":"Hien","l":2410,"q":1}},{"type":"npc","id":"1021693","obj":{"i":1021693,"n":"Lyse","l":2410,"q":1}},{"type":"quest","id":"68053","obj":{"i":68053,"n":"In Crimson They Walked","g":6,"l":"The Azim Steppe","s":750}},{"type":"quest","id":"68055","obj":{"i":68055,"n":"The Room Where It Happened","g":6,"l":"Yanxia","s":770}}]}