{"quest":{"name":"Hand-me-downs","location":"The Rak'tika Greatwood","id":69013,"patch":5.0,"sort":5170,"eventIcon":71221,"issuer":1031395,"target":1031395,"genre":117,"journal":["<span class=\"highlight-red\"> Quest Sync</span><br>The hasty hunter remembers how helpful you can be."],"objectives":["Slay a cracked Ronkan doll for its core.","Deliver the core to the hasty hunter."],"dialogue":[{"name":"FANOWHUNTER03477","text":"A welcome sight in my hour of need."},{"name":"FANOWHUNTER03477","text":"As you know, a number of our stone sentinels have turned against us. But if they can be slain, they may yet serve to protect these ruins."},{"name":"FANOWHUNTER03477","text":"We lack the knowledge to build more, but it is possible to use their parts to repair those that yet remain. "},{"name":"FANOWHUNTER03477","text":"If you could slay even a single sentinel and bring me its core, that is all I require to begin my work. "},{"name":"FANOWHUNTER03477","text":"I only require a single core to begin my work."},{"name":"FANOWHUNTER03477","text":"Do you have a core?"},{"name":"FANOWHUNTER03477","text":"Yes, this is perfect."},{"name":"FANOWHUNTER03477","text":"As I said before, we lack the knowledge to build the sentinels. And this is perhaps the most difficult piece to replicate."},{"name":"FANOWHUNTER03477","text":"So long as their cores can be retrieved, we can prolong the life of those we yet have."}],"reward":{"gil":606},"reqs":{"jobs":[{"lvl":70,"id":34}],"quests":[69012]}},"partials":[{"type":"npc","id":"1031395","obj":{"i":1031395,"n":"Hasty Hunter","l":2957,"q":2}},{"type":"quest","id":"69012","obj":{"i":69012,"n":"Rock Solid","g":117,"l":"The Rak'tika Greatwood","s":5160}}]}